django_peertube_runner_connector/__init__.py
django_peertube_runner_connector/admin.py
django_peertube_runner_connector/apps.py
django_peertube_runner_connector/factories.py
django_peertube_runner_connector/forms.py
django_peertube_runner_connector/models.py
django_peertube_runner_connector/serializers.py
django_peertube_runner_connector/socket.py
django_peertube_runner_connector/storage.py
django_peertube_runner_connector/transcode.py
django_peertube_runner_connector/transcript.py
django_peertube_runner_connector/urls.py
django_peertube_runner_connector/management/commands/__init__.py
django_peertube_runner_connector/management/commands/create_runner_registration_token.py
django_peertube_runner_connector/management/commands/list_runner_registration_token.py
django_peertube_runner_connector/migrations/0001_initial.py
django_peertube_runner_connector/migrations/0002_video_basefilename.py
django_peertube_runner_connector/migrations/0003_runnerjob_domain_alter_runnerjob_error.py
django_peertube_runner_connector/migrations/0004_video_language_video_transcriptfilename_and_more.py
django_peertube_runner_connector/migrations/__init__.py
django_peertube_runner_connector/socketio/__init__.py
django_peertube_runner_connector/socketio/manager.py
django_peertube_runner_connector/utils/__init__.py
django_peertube_runner_connector/utils/ffprobe.py
django_peertube_runner_connector/utils/files.py
django_peertube_runner_connector/utils/request.py
django_peertube_runner_connector/utils/resolutions.py
django_peertube_runner_connector/utils/thumbnail.py
django_peertube_runner_connector/utils/video_state.py
django_peertube_runner_connector/utils/job_handlers/__init__.py
django_peertube_runner_connector/utils/job_handlers/abstract_job_handler.py
django_peertube_runner_connector/utils/job_handlers/abstract_vod_transcoding_job_handler.py
django_peertube_runner_connector/utils/job_handlers/get_job_handler.py
django_peertube_runner_connector-0.12.1.dist-info/LICENSE
django_peertube_runner_connector-0.12.1.dist-info/METADATA
django_peertube_runner_connector-0.12.1.dist-info/WHEEL
django_peertube_runner_connector-0.12.1.dist-info/top_level.txt
django_peertube_runner_connector-0.12.1.dist-info/zip-safe
django_peertube_runner_connector-0.12.1.dist-info/RECORD
