Metadata-Version: 2.1
Name: django_peertube_runner_connector
Version: 0.12.1
Summary: A django application to connect to a peertube runner and transcode videos
Home-page: https://github.com/openfun/django-peertube-runner-connector
Author: Open FUN (France Universite Numerique)
Author-email: fun.dev@fun-mooc.fr
License: MIT
Keywords: peertube,transcode
Classifier: Development Status :: 5 - Production/Stable
Classifier: Framework :: Django
Classifier: Framework :: Django :: 4.2
Classifier: Framework :: Django :: 5.0
Classifier: Intended Audience :: Education
Classifier: Intended Audience :: Developers
Classifier: License :: OSI Approved :: MIT License
Classifier: Programming Language :: Python
Classifier: Programming Language :: Python :: 3
Classifier: Programming Language :: Python :: 3.10
Classifier: Programming Language :: Python :: 3.11
Classifier: Programming Language :: Python :: 3.12
Classifier: Programming Language :: Python :: 3 :: Only
License-File: LICENSE
Requires-Dist: django<6,>=4.2
Requires-Dist: djangorestframework<4,>=3
Requires-Dist: ffmpeg-python<1,>=0.2.0
Requires-Dist: python-socketio<6,>=5
Requires-Dist: django-storages<2,>=1
Requires-Dist: boto3<2,>=1.9
Requires-Dist: websockets<14,>=13
Requires-Dist: redis<6,>=5.0.0
Provides-Extra: dev
Requires-Dist: bandit==1.7.10; extra == "dev"
Requires-Dist: black==24.10.0; extra == "dev"
Requires-Dist: check-manifest==0.50; extra == "dev"
Requires-Dist: cryptography==43.0.3; extra == "dev"
Requires-Dist: flake8==7.1.1; extra == "dev"
Requires-Dist: httpretty==1.1.4; extra == "dev"
Requires-Dist: ipython==8.28.0; extra == "dev"
Requires-Dist: isort==5.13.2; extra == "dev"
Requires-Dist: pycodestyle==2.12.1; extra == "dev"
Requires-Dist: pylint==3.3.1; extra == "dev"
Requires-Dist: pylint-pytest==1.1.8; extra == "dev"
Requires-Dist: pyOpenSSL==24.2.1; extra == "dev"
Requires-Dist: pytest==8.2.0; extra == "dev"
Requires-Dist: pytest-cov==5.0.0; extra == "dev"
Requires-Dist: pytest-django==4.9.0; extra == "dev"
Requires-Dist: pytest-mock==3.14.0; extra == "dev"
Requires-Dist: signxml==4.0.2; extra == "dev"
Requires-Dist: tox; extra == "dev"
Requires-Dist: wheel==0.44.0; extra == "dev"
Requires-Dist: django-configurations==2.5.1; extra == "dev"
Requires-Dist: uvicorn==0.32.0; extra == "dev"
Requires-Dist: factory-boy==3.3.1; extra == "dev"
Requires-Dist: whitenoise==6.7.0; extra == "dev"
